stidantic/__init__.py
stidantic/bundle.py
stidantic/extension.py
stidantic/language.py
stidantic/marking.py
stidantic/sco.py
stidantic/sdo.py
stidantic/serializers.py
stidantic/sro.py
stidantic/types.py
stidantic/utils.py
stidantic/validators.py
stidantic/vocab.py
stidantic/extensions/__init__.py
stidantic/extensions/pap.py
stidantic-0.3.0.dist-info/METADATA
stidantic-0.3.0.dist-info/WHEEL
stidantic-0.3.0.dist-info/licenses/LICENSE
stidantic-0.3.0.dist-info/RECORD
