Metadata-Version: 2.4
Name: stidantic
Version: 0.3.0
Summary: A Pydantic-based Python library for parsing, validating, and creating STIX 2.1 cyber threat intelligence data.
Project-URL: Homepage, https://github.com/nicocti/stidantic
Project-URL: Bug Tracker, https://github.com/nicocti/stidantic/issues
Author-email: nicocti <nicocti@users.noreply.github.com>
Maintainer-email: nicocti <nicocti@users.noreply.github.com>
License-File: LICENSE
Keywords: cti,pydantic,stix,stix2,stix2.1
Classifier: Development Status :: 3 - Alpha
Classifier: Intended Audience :: Developers
Classifier: Intended Audience :: Information Technology
Classifier: License :: OSI Approved :: MIT License
Classifier: Operating System :: OS Independent
Classifier: Programming Language :: Python :: 3
Classifier: Programming Language :: Python :: 3.12
Classifier: Programming Language :: Python :: 3.13
Classifier: Topic :: Security
Classifier: Topic :: Software Development :: Libraries :: Python Modules
Classifier: Typing :: Typed
Requires-Python: >=3.12
Requires-Dist: annotated-types>=0.6.0
Requires-Dist: pydantic>=2.12
Requires-Dist: typing-extensions>=4.14.1
Provides-Extra: dev
Requires-Dist: basedpyright; extra == 'dev'
Provides-Extra: test
Requires-Dist: deepdiff; extra == 'test'
